{
  "data": [
    {
      "id": 2,
      "username": "pop",
      "password": "54321",
      "con_password": "54321",
      "firstname": "pop",
      "lastname": "janny",
      "email": "pop@gmail.com",
      "tel": "0938765431",
      "url": "http://placekitten.com/g/200/200"
    },
    {
      "username": "ice",
      "password": "iceice",
      "con_password": "iceice",
      "firstname": "ice",
      "lastname": "ice",
      "email": "ice@gmail.com",
      "tel": "0123456789",
      "url": "http://placekitten.com/g/200/200",
      "id": 3
    },
    {
      "username": "",
      "password": "",
      "con_password": "",
      "firstname": "",
      "lastname": "",
      "email": "",
      "tel": "",
      "id": 4
    }
  ]
}